AJAS/__init__.py
AJAS/api.py
AJAS/authenticator.py
AJAS/block.py
AJAS/exceptions.py
AJAS/serializer.py
AJAS-0.2.3.dist-info/METADATA
AJAS-0.2.3.dist-info/WHEEL
AJAS-0.2.3.dist-info/top_level.txt
AJAS-0.2.3.dist-info/RECORD
