Metadata-Version: 2.1
Name: AJAS
Version: 0.2.3
Summary: Lightweight REST Sever framework, based on bottle
Home-page: https://github.com/swip3798/AJAS
Author: Christian Schweigel
Author-email: 
License: UNKNOWN
Platform: UNKNOWN
Classifier: Programming Language :: Python :: 3
Classifier: Programming Language :: Python :: 3 :: Only
Classifier: License :: OSI Approved :: GNU Lesser General Public License v3 (LGPLv3)
Classifier: Operating System :: OS Independent
Classifier: Development Status :: 3 - Alpha
Requires-Dist: bottle (==0.12.16)
Requires-Dist: gevent (==1.4.0)
Requires-Dist: Flask (==1.0.3)
